[
  {
    "senderKeyId": 1397958877,
    "senderChainKey": {
      "iteration": 119,
      "seed": "rcKSKW7qLxh6qIyV/uIfO4IW7cytJ9ep/dchpuzI4+c="
    },
    "senderSigningKey": {
      "public": "BSfKpYJr2NXuhLLcLnXxTgyl/W/rycnXOmWCDXirgzx6"
    },
    "senderMessageKeys": []
  },
  {
    "senderKeyId": 997588016,
    "senderChainKey": {
      "iteration": 267,
      "seed": "BvUcjUpstk/wC6JeVZxhemrFSYKLbZ6rZWxdmnkVWOg="
    },
    "senderSigningKey": {
      "public": "Bb8RpCbGTyL4H2osJs7PVuVDTHX040mP4ikM8XzPUm15"
    },
    "senderMessageKeys": [
      {},
      {},
      {},
      {},
      {},
      {},
      {},
      {},
      {},
      {},
      {},
      {},
      {},
      {},
      {},
      {},
      {},
      {},
      {},
      {},
      {},
      {},
      {},
      {},
      {},
      {},
      {},
      {},
      {},
      {},
      {},
      {}
    ]
  },
  {
    "senderKeyId": 997588016,
    "senderChainKey": {
      "iteration": 51,
      "seed": "unhhtjx4JGRK0jR4OQW3SuJH6H574G/nG53A709kgD8="
    },
    "senderSigningKey": {
      "public": "Bb8RpCbGTyL4H2osJs7PVuVDTHX040mP4ikM8XzPUm15"
    },
    "senderMessageKeys": []
  },
  {
    "senderKeyId": 1414507015,
    "senderChainKey": {
      "iteration": 298,
      "seed": "jZGoDgwGu1S4/Oj0AtBWwngEYcB3ZXZ2hCTuybHtM/U="
    },
    "senderSigningKey": {
      "public": "Be8ry7Yg4vAf+PdGsh7qRfdVAgi3fm2Ix6lBKVhZpXMN"
    },
    "senderMessageKeys": [{}, {}, {}, {}, {}, {}, {}, {}, {}, {}, {}, {}]
  },
  {
    "senderKeyId": 1414507015,
    "senderChainKey": {
      "iteration": 185,
      "seed": "IXo/bRFwASFcoG5AoI61c2ZPg6P8dkqVBLbIf1vnBeI="
    },
    "senderSigningKey": {
      "public": "Be8ry7Yg4vAf+PdGsh7qRfdVAgi3fm2Ix6lBKVhZpXMN"
    },
    "senderMessageKeys": []
  },
  {
    "senderKeyId": 1414507015,
    "senderChainKey": {
      "iteration": 209,
      "seed": "PUyUz37RhZZ9dggb9svOswe9N/r3h3xqB07NZ6NkKpk="
    },
    "senderSigningKey": {
      "public": "Be8ry7Yg4vAf+PdGsh7qRfdVAgi3fm2Ix6lBKVhZpXMN"
    },
    "senderMessageKeys": []
  },
  {
    "senderKeyId": 1414507015,
    "senderChainKey": {
      "iteration": 248,
      "seed": "KF5G0qSrEQzjm3xMlmyHtzZh64SponCoVlfbI/8eaQo="
    },
    "senderSigningKey": {
      "public": "Be8ry7Yg4vAf+PdGsh7qRfdVAgi3fm2Ix6lBKVhZpXMN"
    },
    "senderMessageKeys": []
  }
]
